libarc1/__init__.py
libarc1/arc.py
libarc1/log.py
libarc1/modules/__init__.py
libarc1/modules/chronoamperometry.py
libarc1/modules/convergetostate.py
libarc1/modules/curvetracer.py
libarc1/modules/endurance.py
libarc1/modules/formfinder.py
libarc1/modules/multibias.py
libarc1/modules/readops.py
libarc1/modules/switchseeker.py
libarc1/packets.py
libarc1/params.py
libarc1/selector.py
libarc1/sequence.py
libarc1-0.1.0.dist-info/LICENSE
libarc1-0.1.0.dist-info/WHEEL
libarc1-0.1.0.dist-info/METADATA
libarc1-0.1.0.dist-info/RECORD
