Metadata-Version: 2.1
Name: libarc1
Version: 0.1.0
Summary: Minimal interface library to ArC1
Home-page: https://www.arc-instruments.co.uk/products/arc-one/
License: LGPL-3.0-or-later
Author: Spyros Stathopoulos
Author-email: devel@arc-instruments.co.uk
Requires-Python: >=3.6,<4.0
Classifier: Development Status :: 3 - Alpha
Classifier: License :: OSI Approved :: GNU Lesser General Public License v3 or later (LGPLv3+)
Classifier: Programming Language :: Python :: 3
Classifier: Programming Language :: Python :: 3.6
Classifier: Programming Language :: Python :: 3.7
Classifier: Programming Language :: Python :: 3.8
Classifier: Programming Language :: Python :: 3.9
Classifier: Topic :: Scientific/Engineering
Classifier: Topic :: Software Development :: Libraries
Classifier: Topic :: Software Development :: Libraries :: Python Modules
Classifier: Topic :: System :: Hardware
Requires-Dist: dataclasses (>=0.7,<0.8); python_version >= "3.6" and python_version < "3.7"
Requires-Dist: numpy (>=1.14,<2.0)
Requires-Dist: pyserial (>=3.0,<4.0)
Project-URL: Bug Tracker, https://github.com/arc-instruments/libarc1/issues
Project-URL: Repository, https://github.com/arc-instruments/libarc1
